CellMarker_Vis/__init__.py
CellMarker_Vis-0.0.0.1.dist-info/METADATA
CellMarker_Vis-0.0.0.1.dist-info/WHEEL
CellMarker_Vis-0.0.0.1.dist-info/top_level.txt
CellMarker_Vis-0.0.0.1.dist-info/RECORD
