Metadata-Version: 2.1
Name: CellMarker-Vis
Version: 0.0.0.1
Summary: cell type annotation for single cell dataset.
Home-page: https://github.com/wangzichenbioinformatics/CellMarker-Vis
Author: Wangchen
Author-email: wch_bioinformatics@163.com
License: UNKNOWN
Platform: UNKNOWN
Classifier: Programming Language :: Python :: 3
Classifier: License :: OSI Approved :: MIT License
Classifier: Operating System :: OS Independent
Requires-Python: >=3.9
